tj_kits_forest/__init__.py
tj_kits_forest/tj_kits.py
tj_kits_forest-0.0.6.dist-info/METADATA
tj_kits_forest-0.0.6.dist-info/WHEEL
tj_kits_forest-0.0.6.dist-info/top_level.txt
tj_kits_forest-0.0.6.dist-info/RECORD
