Metadata-Version: 2.1
Name: tj-kits-forest
Version: 0.0.6
Summary: Some Kits
Home-page: https://github.com/TJNo-1/tj_kits_forest.git
Author: tjno-1
Author-email: tjno-1@qq.com
License: MIT
Keywords: python,build-in-module kits
